tests/__init__.py
tests/test_data.py
txlink/__init__.py
txlink/data.py
txlink-0.1.0.dist-info/METADATA
txlink-0.1.0.dist-info/WHEEL
txlink-0.1.0.dist-info/top_level.txt
txlink-0.1.0.dist-info/RECORD
