Metadata-Version: 2.4
Name: TxLink
Version: 0.1.0
Summary: TxLink,一个基于python的通信框架,支持多种业务场景模式,广泛应用于分布式量化交易系统构建中
Home-page: https://github.com/95ge/TxLink
Author: 95ge
Author-email: litaoflyme@163.com
Classifier: Programming Language :: Python :: 3
Classifier: License :: OSI Approved :: MIT License
Classifier: Operating System :: OS Independent
Requires-Python: >=3.0
Dynamic: author
Dynamic: author-email
Dynamic: classifier
Dynamic: description
Dynamic: description-content-type
Dynamic: home-page
Dynamic: requires-python
Dynamic: summary
